README.rst
setup.py
bin/launchMMinte
mminte/__init__.py
mminte/community.py
mminte/interaction_analysis.py
mminte/interaction_worker.py
mminte/representative.py
mminte/visualize.py
mminte.egg-info/PKG-INFO
mminte.egg-info/SOURCES.txt
mminte.egg-info/dependency_links.txt
mminte.egg-info/requires.txt
mminte.egg-info/top_level.txt
mminte/data/db/16Sdb.nhr
mminte/data/db/16Sdb.nin
mminte/data/db/16Sdb.nsd
mminte/data/db/16Sdb.nsi
mminte/data/db/16Sdb.nsq
mminte/notebooks/interactions.ipynb
mminte/notebooks/tutorial.ipynb
mminte/site/MMinteIntro.py
mminte/site/MMinteW1.py
mminte/site/MMinteW2.py
mminte/site/MMinteW3.py
mminte/site/MMinteW4.py
mminte/site/MMinteW5.py
mminte/site/MMinteW6.py
mminte/site/MMinteWall.py
mminte/site/__init__.py
mminte/site/mminte_widget.py
mminte/site/static/d3.v3.min.js
mminte/site/static/flow.jpg
mminte/site/static/intro.html
mminte/site/static/logo.jpg
mminte/site/static/mminte_style.css
mminte/site/static/plot.html
mminte/site/static/style.html
mminte/test/__init__.py
mminte/test/conftest.py
mminte/test/test_interactions.py
mminte/test/test_representative.py
mminte/test/data/BT.sbml
mminte/test/data/FP.sbml
mminte/test/data/HP.sbml
mminte/test/data/KP.sbml
mminte/test/data/all_otus.fasta
mminte/test/data/correlation.txt
mminte/test/data/correlation_fields.txt
mminte/test/data/correlation_value.txt
mminte/test/data/diet_fields.txt
mminte/test/data/diet_value.txt
mminte/test/data/missing.fasta
mminte/test/data/ms_complete1.txt
mminte/test/data/ms_complete10.txt
mminte/test/data/ms_complete100.txt
mminte/test/data/western.json