Metadata-Version: 1.1
Name: mminte
Version: 1.0.2
Summary: Microbial Metabolic interactions
Home-page: https://github.com/mendessoares/mminte
Author: Helena Mendes-Soares, Michael Mundy, Luis Mendes Soares, Nicholas Chia
Author-email: microbialmetabolicinteractions@gmail.com
License: BSD
Download-URL: https://pypi.python.org/pypi/mminte
Keywords: metabolism biology optimization flux balance analysis fba
Platform: GNU/Linux
Platform: Mac OS X >= 10.7
Platform: Microsoft Windows >= 7
Classifier: Development Status :: 4 - Beta
Classifier: Environment :: Console
Classifier: Intended Audience :: Science/Research
Classifier: License :: OSI Approved :: BSD License
Classifier: Operating System :: OS Independent
Classifier: Programming Language :: Python :: 2.7
Classifier: Programming Language :: Python :: 3.4
Classifier: Programming Language :: Python :: 3.5
Classifier: Topic :: Scientific/Engineering
Classifier: Topic :: Scientific/Engineering :: Bio-Informatics
